pycoreconf/__init__.py
pycoreconf/pycoreconf.py
pycoreconf/sid.py
pycoreconf-0.0.6.dist-info/LICENSE
pycoreconf-0.0.6.dist-info/METADATA
pycoreconf-0.0.6.dist-info/WHEEL
pycoreconf-0.0.6.dist-info/top_level.txt
pycoreconf-0.0.6.dist-info/RECORD
