Metadata-Version: 2.1
Name: pycoreconf
Version: 0.0.6
Summary: open-source implementation of CORECONF (CoAP Management Interface)
Home-page: https://github.com/alex-fddz/pycoreconf
Author: Javier A. Fernandez
Author-email: javier.fddz@gmail.com
License: UNKNOWN
Project-URL: Source Code, https://github.com/alex-fddz/pycoreconf
Project-URL: Bug Tracker, https://github.com/alex-fddz/pycoreconf/issues
Keywords: coreconf,comi,coap,yang
Platform: UNKNOWN
Classifier: Development Status :: 2 - Pre-Alpha
Classifier: Programming Language :: Python :: 3
Classifier: Operating System :: OS Independent
Requires-Python: <4,>=3.7
License-File: LICENSE
Requires-Dist: cbor2
